bluesky/__init__.py
bluesky/api.py
bluesky/models.py
bluesky/utils.py
bluesky_python-0.0.2.dist-info/METADATA
bluesky_python-0.0.2.dist-info/WHEEL
bluesky_python-0.0.2.dist-info/top_level.txt
bluesky_python-0.0.2.dist-info/RECORD
